setup.cfg
setup.py
letsencrypt_redis/__init__.py
letsencrypt_redis/authenticator.py
letsencrypt_redis/installer.py
letsencrypt_redis.egg-info/PKG-INFO
letsencrypt_redis.egg-info/SOURCES.txt
letsencrypt_redis.egg-info/dependency_links.txt
letsencrypt_redis.egg-info/entry_points.txt
letsencrypt_redis.egg-info/requires.txt
letsencrypt_redis.egg-info/top_level.txt