Metadata-Version: 1.1
Name: letsencrypt-redis
Version: 0.0.1
Summary: Add challenge token to Redis
Home-page: https://github.com/hostinger/letsencrypt-redis
Author: UNKNOWN
Author-email: UNKNOWN
License: UNKNOWN
Download-URL: https://github.com/hostinger/letsencrypt-redis/tarball/0.0.1
Platform: UNKNOWN
